argus/__init__.py
argus/cli.py
argus/core.py
argus/daemon.py
argus_wifi-2.0.0.dist-info/licenses/LICENSE
argus_wifi-2.0.0.dist-info/METADATA
argus_wifi-2.0.0.dist-info/WHEEL
argus_wifi-2.0.0.dist-info/entry_points.txt
argus_wifi-2.0.0.dist-info/top_level.txt
argus_wifi-2.0.0.dist-info/RECORD
