Metadata-Version: 2.4
Name: argus-wifi
Version: 2.0.0
Summary: Argus: WiFi Uptime and Bandwidth Monitor
Author-email: SahooBishwajeet <biswa.2004.bdk@gmail.com>
License: The MIT License (MIT)
Classifier: Programming Language :: Python :: 3
Classifier: Programming Language :: Python :: 3.7
Classifier: Programming Language :: Python :: 3.8
Classifier: Programming Language :: Python :: 3.9
Classifier: Programming Language :: Python :: 3.10
Classifier: Programming Language :: Python :: 3.11
Classifier: License :: OSI Approved :: MIT License
Requires-Python: >=3.7
License-File: LICENSE
Requires-Dist: speedtest-cli
Requires-Dist: pandas
Requires-Dist: matplotlib
Requires-Dist: psutil
Dynamic: license-file
